blint/__init__.py
blint/cli.py
blint/config.py
blint/cyclonedx/README.md
blint/cyclonedx/__init__.py
blint/cyclonedx/spdx.py
blint/cyclonedx/spec.py
blint/data/__init__.py
blint/data/annotations/__init__.py
blint/data/annotations/review_entries_generic.yml
blint/data/annotations/review_entries_pe.yml
blint/data/annotations/review_exe_go.yml
blint/data/annotations/review_functions_generic.yml
blint/data/annotations/review_imports_pe.yml
blint/data/annotations/review_methods_generic.yml
blint/data/annotations/review_methods_mips.yml
blint/data/annotations/review_monero_generic.yml
blint/data/annotations/review_monero_go.yml
blint/data/annotations/review_monero_rust.yml
blint/data/annotations/review_rootkits_win.yml
blint/data/annotations/review_symbols_antiforensic.yml
blint/data/annotations/review_symbols_generic.yml
blint/data/annotations/review_symbols_hooka.yml
blint/data/annotations/review_symbols_macho.yml
blint/data/annotations/review_symbols_rust.yml
blint/data/rules.yml
blint/db.py
blint/lib/__init__.py
blint/lib/analysis.py
blint/lib/android.py
blint/lib/binary.py
blint/lib/checks.py
blint/lib/disassembler.py
blint/lib/runners.py
blint/lib/sbom.py
blint/lib/utils.py
blint/logger.py
blint-3.0.5.dist-info/METADATA
blint-3.0.5.dist-info/WHEEL
blint-3.0.5.dist-info/entry_points.txt
blint-3.0.5.dist-info/licenses/LICENSE
blint-3.0.5.dist-info/RECORD
