Metadata-Version: 2.4
Name: blint
Version: 3.0.5
Summary: Linter and SBOM generator for binary files.
License-Expression: MIT
License-File: LICENSE
Keywords: linter,binary,security,sast
Author: Team AppThreat
Author-email: cloud@appthreat.com
Requires-Python: >=3.10,<3.14
Classifier: Development Status :: 5 - Production/Stable
Classifier: Intended Audience :: Developers
Classifier: Intended Audience :: System Administrators
Classifier: Topic :: Utilities
Classifier: Topic :: Security
Classifier: Programming Language :: Python :: 3.10
Classifier: Programming Language :: Python :: 3.11
Classifier: Programming Language :: Python :: 3.12
Classifier: Programming Language :: Python :: 3.13
Classifier: Operating System :: OS Independent
Provides-Extra: dev
Requires-Dist: PyYAML (>=6.0.2)
Requires-Dist: appdirs (>=1.4.4)
Requires-Dist: apsw (>=3.49.1.0)
Requires-Dist: ar (>=1.0.0)
Requires-Dist: black (>=25.1.0) ; extra == "dev"
Requires-Dist: custom-json-diff (>=2.1.6)
Requires-Dist: defusedxml (>=0.7.1)
Requires-Dist: flake8 (>=7.2.0) ; extra == "dev"
Requires-Dist: lief (>=0.16.6)
Requires-Dist: oras (>=0.2.28)
Requires-Dist: orjson (>=3.10.16)
Requires-Dist: packageurl-python (>=0.16.0)
Requires-Dist: pydantic[email] (>=2.11.3)
Requires-Dist: pyinstaller (>=6.12.0) ; extra == "dev"
Requires-Dist: pylint (>=3.3.6) ; extra == "dev"
Requires-Dist: pytest (>=8.3.5) ; extra == "dev"
Requires-Dist: pytest-cov (>=6.1.1) ; extra == "dev"
Requires-Dist: rich (>=14.0.0)
Requires-Dist: symbolic (==10.2.1)
Project-URL: CI, https://github.com/owasp-dep-scan/blint/actions
